geedatasets/__init__.py
geedatasets/_version.py
geedatasets/bands.py
geedatasets/climate.py
geedatasets/datasets.py
geedatasets/helpers.py
geedatasets/landsat.py
geedatasets/landsat_c1.py
geedatasets/masks.py
geedatasets/modis.py
geedatasets/sentinel.py
geedatasets/visualization.py
geedatasets-0.2.4.dist-info/LICENSE
geedatasets-0.2.4.dist-info/METADATA
geedatasets-0.2.4.dist-info/WHEEL
geedatasets-0.2.4.dist-info/top_level.txt
geedatasets-0.2.4.dist-info/RECORD
