Metadata-Version: 2.1
Name: geedatasets
Version: 0.2.4
Summary: Google Earth Engine Datasets coded in Python for easier manipulation
Home-page: 
Author: Rodrigo E. Principe
Author-email: fitoprincipe82@gmail.com
License: MIT
Keywords: google earth engine raster image processing gis satellite
Classifier: Programming Language :: Python :: 3
Classifier: Programming Language :: Python :: 3.3
Classifier: Programming Language :: Python :: 3.4
Classifier: Programming Language :: Python :: 3.5
Classifier: License :: OSI Approved :: MIT License
License-File: LICENSE
Requires-Dist: geetools
Provides-Extra: dev
Provides-Extra: docs
Provides-Extra: testing
